keybeat/__init__.py
keybeat/analyzer.py
keybeat_txrr-0.1.0.dist-info/licenses/LICENSE
keybeat_txrr-0.1.0.dist-info/METADATA
keybeat_txrr-0.1.0.dist-info/WHEEL
keybeat_txrr-0.1.0.dist-info/top_level.txt
keybeat_txrr-0.1.0.dist-info/RECORD
