Metadata-Version: 2.4
Name: keybeat-txrr
Version: 0.1.0
Summary: Detecta o tom e o BPM de arquivos de áudio (MP3, WAV, FLAC)
Author-email: therealtxr <therealtxr@gmail.com>
License: MIT
Requires-Python: >=3.8
License-File: LICENSE
Requires-Dist: librosa>=0.10.1
Requires-Dist: numpy>=1.24.0
Requires-Dist: soundfile>=0.12.1
Requires-Dist: audioread>=3.0.1
Dynamic: license-file
